snpmatch/__init__.py
snpmatch/core/__init__.py
snpmatch/core/csmatch.py
snpmatch/core/genomes.py
snpmatch/core/genotype_cross.py
snpmatch/core/makedb.py
snpmatch/core/parsers.py
snpmatch/core/simulate.py
snpmatch/core/snp_genotype.py
snpmatch/core/snpmatch.py
snpmatch/resources/genomes/athaliana_tair10.json
SNPmatch-4.0.0.dist-info/LICENSE
SNPmatch-4.0.0.dist-info/METADATA
SNPmatch-4.0.0.dist-info/WHEEL
SNPmatch-4.0.0.dist-info/entry_points.txt
SNPmatch-4.0.0.dist-info/top_level.txt
SNPmatch-4.0.0.dist-info/RECORD
