Metadata-Version: 2.1
Name: SNPmatch
Version: 4.0.0
Summary: A simple python library to identify the most likely strain given the SNPs for a sample
Home-page: https://github.com/Gregor-Mendel-Institute/SNPmatch
Author: ['Rahul Pisupati']
Author-email: rahul.pisupati@gmi.oeaw.ac.at
License: GMI
Keywords: Genotyping Low Coverage sequencing data
Platform: UNKNOWN
Classifier: Development Status :: 5 - Production/Stable
Classifier: Intended Audience :: Developers
Classifier: Topic :: Scientific/Engineering :: Bio-Informatics
Classifier: Programming Language :: Python :: 3.4
Requires-Dist: scipy (>=0.17.0)
Requires-Dist: numpy (>=1.9.0)
Requires-Dist: PyGWAS
Requires-Dist: scikit-allel
Requires-Dist: pandas
